iencode.py
setup.py
iencode_ng.egg-info/PKG-INFO
iencode_ng.egg-info/SOURCES.txt
iencode_ng.egg-info/dependency_links.txt
iencode_ng.egg-info/entry_points.txt
iencode_ng.egg-info/top_level.txt