Metadata-Version: 1.0
Name: iencode-ng
Version: 0.9.5
Summary: iPhone video encoding tools.
Home-page: http://github.com/tuxtof/iencode-ng
Author: tuxtof
Author-email: dev@geo6.net
License: GPLv2
Platform: UNKNOWN
